extra_qt/__init__.py
extra_qt/component.py
extra_qt/dom/__init__.py
extra_qt/dom/qt_dom.py
extra_qt/reconciler.py
extra_qt/renderers/__init__.py
extra_qt/renderers/qt_renderer.py
extra_qt/renderers/renderer.py
extra_qt/virtual_dom.py
extra_qt-0.1.0.dist-info/LICENSE
extra_qt-0.1.0.dist-info/WHEEL
extra_qt-0.1.0.dist-info/METADATA
extra_qt-0.1.0.dist-info/RECORD
